balderhub/auth/__init__.py
balderhub/auth/_version.py
balderhub/auth/contrib/__init__.py
balderhub/auth/contrib/html/__init__.py
balderhub/auth/contrib/html/pages/__init__.py
balderhub/auth/contrib/html/pages/login_page.py
balderhub/auth/contrib/html/setup_features/__init__.py
balderhub/auth/contrib/html/setup_features/user_login_feature.py
balderhub/auth/lib/__init__.py
balderhub/auth/lib/scenario_features/__init__.py
balderhub/auth/lib/scenario_features/user_login_feature.py
balderhub/auth/lib/scenario_features/role/__init__.py
balderhub/auth/lib/scenario_features/role/base_role_feature.py
balderhub/auth/lib/scenario_features/role/token_role_feature.py
balderhub/auth/lib/scenario_features/role/user_role_feature.py
balderhub/auth/lib/setup_features/__init__.py
balderhub/auth/lib/utils/__init__.py
balderhub/auth/scenarios/__init__.py
balderhub/auth/scenarios/scenario_simple_login.py
balderhub/auth/setups/__init__.py
balderhub_auth-0.0.1b0.dist-info/licenses/LICENSE
balderhub_auth-0.0.1b0.dist-info/METADATA
balderhub_auth-0.0.1b0.dist-info/WHEEL
balderhub_auth-0.0.1b0.dist-info/top_level.txt
balderhub_auth-0.0.1b0.dist-info/RECORD
